bytetools/__init__.py
bytetools/exceptions.py
bytetools/operations.c
bytetools/operations.cpython-311-darwin.so
bytetools/operations.py
bytetools-0.1.0.dist-info/LICENSE
bytetools-0.1.0.dist-info/METADATA
bytetools-0.1.0.dist-info/WHEEL
bytetools-0.1.0.dist-info/top_level.txt
bytetools-0.1.0.dist-info/RECORD
